{
  "templates": [
    {
      "name": "homepage",
      "urls": [
        "https://www.business.att.com/"
      ],
      "description": "AT&T Business homepage with hero, product offerings, and promotional content",
      "blocks": [
        {
          "name": "hero-banner",
          "instances": [
            "div.hero.aem-GridColumn:first-of-type"
          ]
        },
        {
          "name": "cards-product",
          "instances": [
            "div.multi-tile-cards:first-of-type .multi-tile-section"
          ]
        },
        {
          "name": "cards-promo",
          "instances": [
            "div.flex-cards .row-of-cards"
          ]
        },
        {
          "name": "cards-value",
          "instances": [
            "div.generic-list-value-prop .generic-list-icon-vp-row"
          ]
        },
        {
          "name": "columns-offer",
          "instances": [
            "div.offer.aem-GridColumn:nth-of-type(1)",
            "div.offer.aem-GridColumn:nth-of-type(2)"
          ]
        },
        {
          "name": "hero-dark",
          "instances": [
            "div.hero.aem-GridColumn:nth-of-type(2)",
            "div.hero.aem-GridColumn:nth-of-type(3)"
          ]
        },
        {
          "name": "carousel-industry",
          "instances": [
            "div.story-stack .storyStackSlider"
          ]
        },
        {
          "name": "cards-story",
          "instances": [
            "div.multi-tile-cards:nth-of-type(2) .multi-tile-section"
          ]
        },
        {
          "name": "accordion-links",
          "instances": [
            "div.link-farm.aem-GridColumn"
          ]
        }
      ],
      "sections": [
        {
          "id": "section-1",
          "name": "Hero Banner",
          "selector": "div.hero.aem-GridColumn:first-of-type",
          "style": null,
          "blocks": [
            "hero-banner"
          ],
          "defaultContent": []
        },
        {
          "id": "section-2",
          "name": "Product Categories",
          "selector": "div.multi-tile-cards.aem-GridColumn:first-of-type",
          "style": null,
          "blocks": [
            "cards-product"
          ],
          "defaultContent": [
            "div.multi-tile-cards:first-of-type .eyebrow-heading-body"
          ]
        },
        {
          "id": "section-3",
          "name": "Promotional Offers",
          "selector": "div.flex-cards.aem-GridColumn",
          "style": null,
          "blocks": [
            "cards-promo"
          ],
          "defaultContent": [
            "div.flex-cards .grid-col-10 h1"
          ]
        },
        {
          "id": "section-4",
          "name": "Value Propositions",
          "selector": "div.generic-list-value-prop.aem-GridColumn",
          "style": null,
          "blocks": [
            "cards-value"
          ],
          "defaultContent": [
            "div.generic-list-value-prop .grid-col-10"
          ]
        },
        {
          "id": "section-5",
          "name": "Customer Satisfaction",
          "selector": "div.offer.aem-GridColumn:nth-of-type(1)",
          "style": "grey",
          "blocks": [
            "columns-offer"
          ],
          "defaultContent": []
        },
        {
          "id": "section-6",
          "name": "Dynamic Defense Hero",
          "selector": "div.hero.aem-GridColumn:nth-of-type(2)",
          "style": null,
          "blocks": [
            "hero-dark"
          ],
          "defaultContent": []
        },
        {
          "id": "section-7",
          "name": "30-Day Trial Banner",
          "selector": "div.micro-banner.aem-GridColumn",
          "style": "accent",
          "blocks": [],
          "defaultContent": [
            "div.micro-banner.aem-GridColumn"
          ]
        },
        {
          "id": "section-8",
          "name": "Switch to AT&T",
          "selector": "div.offer.aem-GridColumn:nth-of-type(2)",
          "style": null,
          "blocks": [
            "columns-offer"
          ],
          "defaultContent": []
        },
        {
          "id": "section-9",
          "name": "Industry Solutions",
          "selector": "div.story-stack.aem-GridColumn",
          "style": null,
          "blocks": [
            "carousel-industry"
          ],
          "defaultContent": [
            "div.story-stack .ss-masterHeader"
          ]
        },
        {
          "id": "section-10",
          "name": "AT&T Guarantee Hero",
          "selector": "div.hero.aem-GridColumn:nth-of-type(3)",
          "style": null,
          "blocks": [
            "hero-dark"
          ],
          "defaultContent": []
        },
        {
          "id": "section-11",
          "name": "Customer Stories",
          "selector": "div.multi-tile-cards.aem-GridColumn:nth-of-type(2)",
          "style": null,
          "blocks": [
            "cards-story"
          ],
          "defaultContent": [
            "div.multi-tile-cards:nth-of-type(2) .eyebrow-heading-body",
            "div.multi-tile-cards:nth-of-type(2) .cta-section"
          ]
        },
        {
          "id": "section-12",
          "name": "Contact Sales Form",
          "selector": "div.rai-form.aem-GridColumn",
          "style": "grey",
          "blocks": [],
          "defaultContent": [
            "div.rai-form .RAIHeader",
            "div.rai-form section.body-section"
          ]
        },
        {
          "id": "section-13",
          "name": "Link Farm",
          "selector": "div.link-farm.aem-GridColumn",
          "style": "grey",
          "blocks": [
            "accordion-links"
          ],
          "defaultContent": []
        }
      ]
    }
  ]
}
